payment_order_renderer-0.1.6.dist-info/METADATA
payment_order_renderer-0.1.6.dist-info/WHEEL
payment_order_renderer-0.1.6.dist-info/license_files/LICENSE
payment_order_renderer/__init__.py
payment_order_renderer/payment_order_renderer.abi3.so
payment_order_renderer-0.1.6.dist-info/RECORD
