Metadata-Version: 2.1
Name: payment_order_renderer
Version: 0.1.6
Classifier: Programming Language :: Rust
Classifier: Programming Language :: Python :: Implementation :: CPython
Classifier: Programming Language :: Python :: Implementation :: PyPy
License-File: LICENSE
Requires-Python: >=3.7
Project-URL: Homepage, https://github.com/LegendarySaiyan/payment_order_renderer
